python_package_table/__init__.py
python_package_table/multiply_table.py
python_package_table-0.1.dist-info/LICENSE.txt
python_package_table-0.1.dist-info/METADATA
python_package_table-0.1.dist-info/WHEEL
python_package_table-0.1.dist-info/top_level.txt
python_package_table-0.1.dist-info/RECORD
