Metadata-Version: 2.1
Name: python-package-table
Version: 0.1
Summary: To get tables by using numbers 
Home-page: UNKNOWN
Author: Murali Mohan
Author-email: UNKNOWN
License: MIT
Keywords: table
Platform: UNKNOWN
Classifier: Development Status :: 5 - Production/Stable
Classifier: Intended Audience :: Education
Classifier: Operating System :: Microsoft :: Windows :: Windows 10
Classifier: License :: OSI Approved :: MIT License
Classifier: Programming Language :: Python :: 3
